{
  "nwb2bids_notifications": {
    "unsanitized": {},
    "basic_sanitization": {}
  },
  "bids_invalidations": {
    "unsanitized": {
      "WARNING": {
        "JSON_KEY_RECOMMENDED": 689,
        "SIDECAR_KEY_RECOMMENDED": 373291,
        "TSV_COLUMN_TYPE_REDEFINED": 33351,
        "SUBJECT_FOLDERS": 355,
        "NO_AUTHORS": 105,
        "SUSPICIOUS_POSITIVE_EVENT_ONSET": 39,
        "EVENT_ONSET_ORDER": 305
      },
      "ERROR": {
        "TSV_VALUE_INCORRECT_TYPE": 1309,
        "INVALID_ENTITY_LABEL": 19793,
        "SIDECAR_KEY_REQUIRED": 42786,
        "NOT_INCLUDED": 36217,
        "PARTICIPANT_ID_MISMATCH": 1,
        "JSON_KEY_REQUIRED": 105,
        "JSON_SCHEMA_VALIDATION_ERROR": 378,
        "SIDECAR_WITHOUT_DATAFILE": 264,
        "TSV_INDEX_VALUE_NOT_UNIQUE": 29568,
        "TSV_EQUAL_ROWS": 305,
        "TSV_COLUMN_MISSING": 613,
        "TSV_COLUMN_ORDER_INCORRECT": 3,
        "TSV_ADDITIONAL_COLUMNS_MUST_DEFINE": 3
      }
    },
    "basic_sanitization": {
      "WARNING": {
        "JSON_KEY_RECOMMENDED": 10,
        "SIDECAR_KEY_RECOMMENDED": 157617,
        "EVENT_ONSET_ORDER": 85,
        "TSV_COLUMN_TYPE_REDEFINED": 21922,
        "NO_AUTHORS": 2,
        "SUBJECT_FOLDERS": 1
      },
      "ERROR": {
        "SIDECAR_KEY_REQUIRED": 18171,
        "TSV_VALUE_INCORRECT_TYPE": 182,
        "PARTICIPANT_ID_MISMATCH": 1,
        "JSON_KEY_REQUIRED": 2,
        "INVALID_ENTITY_LABEL": 7,
        "TSV_COLUMN_ORDER_INCORRECT": 3,
        "TSV_ADDITIONAL_COLUMNS_MUST_DEFINE": 3,
        "TSV_COLUMN_MISSING": 3
      }
    }
  }
}